steps/__init__.py
steps/constants.py
steps/deploy_production_script.py
steps/deploy_staging_script.py
steps/env_setup_step.py
steps/evaluate_script.py
steps/model_explaination_step.py
steps/preprocessing_script.py
steps/register_model_script.py
steps/testing_step.py
steps/train_script.py
steps/utils.py
kgf_azure_ml_model-1.0.dist-info/METADATA
kgf_azure_ml_model-1.0.dist-info/WHEEL
kgf_azure_ml_model-1.0.dist-info/top_level.txt
kgf_azure_ml_model-1.0.dist-info/RECORD
